<video><action begin="259" end="348" /><action begin="940" end="1005" /><action begin="1425" end="1514" /><action begin="1588" end="1712" /><action begin="1746" end="1806" /><action begin="2291" end="2375" /><action begin="2453" end="2545" /><action begin="2631" end="2830" /><action begin="3384" end="3471" /><action begin="3529" end="3599" /><action begin="3670" end="3747" /><action begin="3802" end="3906" /><action begin="4251" end="4338" /><action begin="4421" end="4504" /><action begin="5001" end="5082" /><action begin="5144" end="5232" /><action begin="5665" end="5748" /><action begin="6074" end="6158" /><action begin="6455" end="6527" /><action begin="6954" end="7047" /><action begin="7106" end="7174" /><action begin="7512" end="7606" /><action begin="7855" end="7923" /></video>